homestead/.gitignore
homestead/__init__.py
homestead/core/__init__.py
homestead/core/main.py
homestead/core/routes/__init__.py
homestead/core/routes/bootstrap.py
homestead/core/routes/routing.py
homestead/craft/__init__.py
homestead/craft/commands/__init__.py
homestead/craft/commands/module_commands.py
homestead/craft/commands/project.py
homestead/craft/main.py
homestead/craft/stubs/__init__.py
homestead/craft/stubs/modules/__init__.py
homestead/craft/stubs/modules/api_controller.py
homestead/craft/stubs/modules/model.py
homestead/craft/stubs/modules/schema.py
homestead/craft/stubs/modules/service.py
homestead/craft/stubs/modules/web_controller.py
homestead/craft/stubs/views/stub_view.html
homestead/utils/__init__.py
homestead/utils/filesystem.py
homestead-0.0.3.dist-info/entry_points.txt
homestead-0.0.3.dist-info/LICENSE
homestead-0.0.3.dist-info/WHEEL
homestead-0.0.3.dist-info/METADATA
homestead-0.0.3.dist-info/RECORD
